{
  "$schema": "https://schemas.wp.org/trunk/block.json",
  "apiVersion": 2,
  "name": "create-block/cepheus-videocover-wordpress",
  "version": "0.1.0",
  "title": "Cepheus Videocover Wordpress",
  "category": "widgets",
  "icon": "smiley",
  "description": "Example static block scaffolded with Create Block tool.",
  "supports": {
    "html": false
  },
  "textdomain": "cepheus-videocover-wordpress",
  "editorScript": "file:./index.js",
  "editorStyle": "file:./index.css",
  "style": "file:./style-index.css"
}